ft/__init__.py
ft/command.py
ft/error.py
ft/functions.py
ft/internal.py
ft/termcolor.py
ft/test_command.py
ft/types.py
ft/commands/__init__.py
ft/commands/filter.py
ft/commands/foldl.py
ft/commands/foldl1.py
ft/commands/ft_functions.py
ft/commands/map.py
ft/commands/sort_by.py
ft/commands/take_while.py
shell_functools-0.3.1.dist-info/METADATA
shell_functools-0.3.1.dist-info/WHEEL
shell_functools-0.3.1.dist-info/entry_points.txt
shell_functools-0.3.1.dist-info/licenses/LICENSE
shell_functools-0.3.1.dist-info/RECORD
