Metadata-Version: 2.3
Name: shell-functools
Version: 0.3.1
Summary: A collection of functional programming tools for the shell.
Project-URL: Home, https://github.com/sharkdp/shell-functools
Author-email: David Peter <mail@david-peter.de>
License: MIT
Keywords: command-line,filesystem,functional-programming,shell,string-manipulation
Classifier: Development Status :: 4 - Beta
Classifier: License :: OSI Approved :: MIT License
Classifier: Programming Language :: Python
Classifier: Programming Language :: Python :: 3
Classifier: Programming Language :: Python :: 3 :: Only
Classifier: Programming Language :: Python :: 3.9
Classifier: Programming Language :: Python :: 3.10
Classifier: Programming Language :: Python :: 3.11
Classifier: Programming Language :: Python :: 3.12
Classifier: Programming Language :: Python :: 3.13
Requires-Python: >=3.9
